uliweb_apijson/__init__.py
uliweb_apijson/apijson/README.md
uliweb_apijson/apijson/__init__.py
uliweb_apijson/apijson/config.ini
uliweb_apijson/apijson/settings.ini
uliweb_apijson/apijson/views.py
uliweb_apijson/apijson/static/readme.txt
uliweb_apijson/apijson/templates/readme.txt
uliweb_apijson/apijson/templates/vue/inc_apijson_table.html
uliweb_apijson/apijson/templates/vue/inc_apijson_viewedit.html
uliweb_apijson/tables/README.md
uliweb_apijson/tables/__init__.py
uliweb_apijson/tables/settings.ini
uliweb_apijson/tables/views.py
uliweb_apijson/tables/static/readme.txt
uliweb_apijson/tables/templates/readme.txt
uliweb_apijson/tables/templates/Tables/layout.html
uliweb_apijson/tables/templates/Tables/list.html
uliweb_apijson/tables/templates/Tables/inc/table_config.html
uliweb_apijson-0.3.0.dist-info/LICENSE
uliweb_apijson-0.3.0.dist-info/METADATA
uliweb_apijson-0.3.0.dist-info/WHEEL
uliweb_apijson-0.3.0.dist-info/top_level.txt
uliweb_apijson-0.3.0.dist-info/RECORD
