Metadata-Version: 2.1
Name: uliweb-apijson
Version: 0.3.0
Summary: uliweb-apijson
Home-page: https://github.com/zhangchunlin/uliweb-apijson
Author: Chunlin Zhang
Author-email: zhangchunlin@gmail.com
License: BSD
Platform: any
Classifier: Development Status :: 4 - Beta
Classifier: Environment :: Web Environment
Classifier: Intended Audience :: Developers
Classifier: License :: OSI Approved :: BSD License
Classifier: Operating System :: OS Independent
Classifier: Programming Language :: Python
Classifier: Topic :: Software Development :: Libraries :: Python Modules
